PySubdiv/PySubdiv.py
PySubdiv/__init__.py
PySubdiv/backend/__init__.py
PySubdiv/backend/automatization.py
PySubdiv/backend/calculation.py
PySubdiv/backend/optimization.py
PySubdiv/backend/utils.py
PySubdiv/backend/visualize.py
PySubdiv/create_control_cage/__init__.py
PySubdiv/create_control_cage/control_cage.py
PySubdiv/create_control_cage/vtk_custom_widget.py
PySubdiv/data/__init__.py
PySubdiv/data/data.py
PySubdiv/data/data_structure.py
PySubdiv/data/files.py
PySubdiv/optimization/__init__.py
PySubdiv/optimization/minimization.py
PySubdiv/optimization/optimization_backend/__init__.py
PySubdiv/optimization/optimization_backend/init_csv.py
PySubdiv/optimization/optimization_backend/objective_functions.py
PySubdiv/subdivision_algorithms/Catmull_Clark.py
PySubdiv/subdivision_algorithms/__init__.py
PySubdiv/subdivision_algorithms/loop.py
PySubdiv/subdivision_algorithms/loop_optimization.py
PySubdiv/subdivision_algorithms/simple_subidivsion_triangles.py
PySubdiv/subdivision_algorithms/subdivision_backend/__init__.py
PySubdiv/subdivision_algorithms/subdivision_backend/property_inhertiage.py
PySubdiv/subdivision_algorithms/subdivision_backend/vertex_masks.py
PySubdiv-0.1.dist-info/LICENSE
PySubdiv-0.1.dist-info/METADATA
PySubdiv-0.1.dist-info/WHEEL
PySubdiv-0.1.dist-info/top_level.txt
PySubdiv-0.1.dist-info/RECORD
