Metadata-Version: 2.1
Name: PySubdiv
Version: 0.1
Summary: An Open-source, Python-based software for fitting subdivision surfaces
Home-page: 
Author: Simon Bernard,  S. Mohammad Moulaeifard
Author-email: simon.bernard@rwth-aachen.de, Mohammad.Moulaeifard@cgre.rwth-aachen.de
License-File: LICENSE
Requires-Dist: pyvista (==0.36.1)
Requires-Dist: networkx (>=2.6.3)
Requires-Dist: numpy (>=1.21.4)
Requires-Dist: QtPy (~=2.0.0)
Requires-Dist: PyQt5 (~=5.15.6)
Requires-Dist: vtk (~=9.2.2)
Requires-Dist: scipy (>=1.7.2)
Requires-Dist: pyvistaqt (~=0.9.0)
Requires-Dist: easygui (~=0.98.3)
Requires-Dist: pymeshlab (==2022.2.post2)
Requires-Dist: meshio
Requires-Dist: pyswarms (>=1.3.0)
